[
  {"src": "Berries_Square.jpg", "title": "Morphology", "size": "", "medium": "Pyrography and watercolor on board"},
  {"src": "Berries_1.jpg", "title": "Eclipsed Expectations", "size": "5.5\"x5.5\"", "medium": "Pyrography and watercolor on board"},
  {"src": "Berries_2.jpg", "title": "GREEN", "size": "5.5\"x5.5\"", "medium": "Pyrography and watercolor on board"},
  {"src": "Berries_3.jpg", "title": "Columbine", "size": "5.5\"x5.5\"", "medium": "Pyrography and watercolor on board"},
  {"src": "Berries_4.jpg", "title": "Sketch I", "size": "5.5\"x5.5\"", "medium": "Pyrography and watercolor on board"},
  {"src": "Berries_5.jpg", "title": "Sketch II", "size": "5.5\"x5.5\"", "medium": "Pyrography and watercolor on board"},
  {"src": "Berries_6.jpg", "title": "Coral Bean", "size": "5.5\"x5.5\"", "medium": "Pyrography and watercolor on board"},
  {"src": "Berries_7.jpg", "title": "BAER I", "size": "5.5\"x5.5\"", "medium": "Pyrography and watercolor on board"},
  {"src": "Berries_8.jpg", "title": "BAER II", "size": "5.5\"x5.5\"", "medium": "Pyrography and watercolor on board"},
  {"src": "Berries_9.jpg", "title": "BAER II", "size": "5.5\"x5.5\"", "medium": "Pyrography and watercolor on board"},
  {"src": "Berries_10.jpg", "title": "Berberis fremontii", "size": "5.5\"x5.5\"", "medium": "Pyrography and watercolor on board"}
]